polygphys/__init__.py
polygphys/__main__.py
polygphys/admin/__init__.py
polygphys/admin/heures/__init__.py
polygphys/admin/heures/exporter.py
polygphys/admin/heures/heures.cfg
polygphys/admin/heures/heures.py
polygphys/atelier/__init__.py
polygphys/outils/__init__.py
polygphys/outils/__main__.py
polygphys/outils/journal.py
polygphys/outils/appareils/__init__.py
polygphys/outils/appareils/__main__.py
polygphys/outils/appareils/phs8302.cfg
polygphys/outils/appareils/HP/HP4274A_dev.py
polygphys/outils/appareils/HP/HP4274A_lab.py
polygphys/outils/appareils/HP/__init__.py
polygphys/outils/appareils/Thorlabs/__init__.py
polygphys/outils/appareils/Thorlabs/lab.py
polygphys/outils/base_de_donnees/__init__.py
polygphys/outils/base_de_donnees/__main__.py
polygphys/outils/base_de_donnees/default.cfg
polygphys/outils/base_de_donnees/dtypes.py
polygphys/outils/base_de_donnees/gestion.py
polygphys/outils/base_de_donnees/modeles.py
polygphys/outils/config/__init__.py
polygphys/outils/config/__main__.py
polygphys/outils/config/default.cfg
polygphys/outils/config/json.py
polygphys/outils/config/toml.py
polygphys/outils/config/yaml.py
polygphys/outils/interface_graphique/__init__.py
polygphys/outils/interface_graphique/__main__.py
polygphys/outils/interface_graphique/html.py
polygphys/outils/interface_graphique/tableau.py
polygphys/outils/interface_graphique/tkinter/__init__.py
polygphys/outils/interface_graphique/tkinter/__main__.py
polygphys/outils/interface_graphique/tkinter/onglets.py
polygphys/outils/reseau/__init__.py
polygphys/outils/reseau/__main__.py
polygphys/outils/reseau/courriel.py
polygphys/outils/reseau/msforms.py
polygphys/outils/reseau/serveur/__init__.py
polygphys/serveur/__init__.py
polygphys/serveur/__main__.py
polygphys/serveur/nouveau_script.py
polygphys/serveur/serveur.cfg
polygphys/sst/__init__.py
polygphys/sst/certificat.py
polygphys/sst/certificats_laser/__init__.py
polygphys/sst/certificats_laser/nouveau_certificat.cfg
polygphys-6.0.26.dist-info/METADATA
polygphys-6.0.26.dist-info/WHEEL
polygphys-6.0.26.dist-info/top_level.txt
polygphys-6.0.26.dist-info/RECORD
