Metadata-Version: 2.1
Name: polygphys
Version: 6.0.26
Summary: Outils pour des programmes à l'interne du département de physique de Polytechnique Montréal.
Author: Émile Jetzer
Author-email: emile.jetzer@polymtl.ca
Requires-Python: >=3.11
Requires-Dist: pandas
Requires-Dist: sqlalchemy
Requires-Dist: openpyxl
Requires-Dist: xlwt
Requires-Dist: gitpython
Requires-Dist: pyserial
Requires-Dist: pyusb
Requires-Dist: pyvisa-py
Requires-Dist: pyvisa
Requires-Dist: zipp
Requires-Dist: importlib-metadata
Requires-Dist: docutils
Requires-Dist: tornado
Requires-Dist: cryptography
Requires-Dist: toml
Requires-Dist: keyring
Requires-Dist: numpy
Requires-Dist: brotli
Requires-Dist: Cython
Requires-Dist: lockfile
Requires-Dist: lxml
Requires-Dist: mock
Requires-Dist: ordereddict
Requires-Dist: protobuf
Requires-Dist: pyOpenSSL
Requires-Dist: simplejson
Requires-Dist: wincertstore
Requires-Dist: python-pptx
Requires-Dist: unoconv
Requires-Dist: paramiko
Requires-Dist: databases
Requires-Dist: ics
Requires-Dist: matplotlib
Requires-Dist: plistop >=0.2
Requires-Dist: python-usbtmc
Requires-Dist: schedule
Requires-Dist: pymysql
Requires-Dist: requests
Requires-Dist: platformdirs
Requires-Dist: chardet
